[{
  "question": {
    "section": "JavaScript",
    "theme": "Array",
    "text": "Короткий синтаксис создания массива?",
    "time": 20,
    "answer": "[]"
  },
  "answer": {
    "time": "",
    "text": ""
  }
},
{
  "question": {
    "section": "JavaScript",
    "theme": "Array",
    "text": "Создайте новый объект через функцию конструктор?",
    "time": 20,
    "answer": "new Aray()"
  },
  "answer": {
    "time": "",
    "text": ""
  }
},
{
  "question": {
    "section": "JavaScript",
    "theme": "Array",
    "text": "Для массива <span>arr</span> найдите длину?",
    "time": 20,
    "answer": "arr.length"
  },
  "answer": {
    "time": "",
    "text": ""
  }
},
{
  "question": {
    "section": "JavaScript",
    "theme": "Array",
    "text": "В массиве <span>arr</span> удалите последний элемент?",
    "time": 20,
    "answer": "arr.pop()"
  },
  "answer": {
    "time": "",
    "text": ""
  }
},
{
  "question": {
    "section": "JavaScript",
    "theme": "Array",
    "text": "В массиве <span>arr</span> добавьте элемент <span>new</span> в конец массива?",
    "time": 20,
    "answer": "arr.push(new)"
  },
  "answer": {
    "time": "",
    "text": ""
  }
},
{
  "question": {
    "section": "JavaScript",
    "theme": "Array",
    "text": "Из массива <span>arr</span> удалить первый элемент?",
    "time": 20,
    "answer": "arr.shift(0)"
  },
  "answer": {
    "time": "",
    "text": ""
  }
},
{
  "question": {
    "section": "JavaScript",
    "theme": "Array",
    "text": "В начало массива <span>arr</span> добавить элемент <span>2</span>?",
    "time": 20,
    "answer": "arr.unshift(2)"
  },
  "answer": {
    "time": "",
    "text": ""
  }
},
{
  "question": {
    "section": "JavaScript",
    "theme": "Array",
    "text": "Скопировать массив <span>arr</span> со 2 по 5 позицию включительно?",
    "time": 20,
    "answer": "arr.slice(1, 6)"
  },
  "answer": {
    "time": "",
    "text": ""
  }
},
{
  "question": {
    "section": "JavaScript",
    "theme": "Array",
    "text": "В массиве <span>arr</span> удалить <span>2</span> элемента с позиции <span>1</span> и заменить их на элементы <span>3, 4</span>?",
    "time": 20,
    "answer": "arr.splice(1, 2, 3, 4)"
  },
  "answer": {
    "time": "",
    "text": ""
  }
},
{
  "question": {
    "section": "JavaScript",
    "theme": "Array",
    "text": "Разбить строку <span>str</span> по разделителю <span>-</span>?",
    "time": 20,
    "answer": "str.split('-')"
  },
  "answer": {
    "time": "",
    "text": ""
  }
},
{
  "question": {
    "section": "JavaScript",
    "theme": "Array",
    "text": "Объединить массив <span>arr</span> в строку с разделителем <span>-</span>?",
    "time": 20,
    "answer": "arr.join('-')"
  },
  "answer": {
    "time": "",
    "text": ""
  }
},
{
  "question": {
    "section": "JavaScript",
    "theme": "Array",
    "text": "Сортировать массив <span>arr</span> как строки?",
    "time": 20,
    "answer": "arr.sort()"
  },
  "answer": {
    "time": "",
    "text": ""
  }
},
{
  "question": {
    "section": "JavaScript",
    "theme": "Array",
    "text": "Развернуть массив <span>arr</span> задом на перед?",
    "time": 20,
    "answer": "arr.reverse()"
  },
  "answer": {
    "time": "",
    "text": ""
  }
},
{
  "question": {
    "section": "JavaScript",
    "theme": "Array",
    "text": "Добавить в массив <span>arr</span> еще массивы <span>arr1</span>, <span>arr2</span>?",
    "time": 20,
    "answer": "arr.concat(arr1, arr2)"
  },
  "answer": {
    "time": "",
    "text": ""
  }
},
{
  "question": {
    "section": "JavaScript",
    "theme": "Array",
    "text": "Найти в массиве <span>arr</span> элемент <span>'obj'</span>?",
    "time": 20,
    "answer": "arr.indexOf('obj')"
  },
  "answer": {
    "time": "",
    "text": ""
  }
},
{
  "question": {
    "section": "JavaScript",
    "theme": "Array",
    "text": "Применить функцию <span>func</span> для каждого элемента массива <span>arr</span>?",
    "time": 20,
    "answer": "arr.forEach(func)"
  },
  "answer": {
    "time": "",
    "text": ""
  }
},
{
  "question": {
    "section": "JavaScript",
    "theme": "Array",
    "text": "Отфильтровать массив <span>arr</span> функцией <span>func</span>?",
    "time": 20,
    "answer": "arr.filter(func)"
  },
  "answer": {
    "time": "",
    "text": ""
  }
},
{
  "question": {
    "section": "JavaScript",
    "theme": "Array",
    "text": "Создание нового массива из результатов вызова функции <span>func</span> для массива <span>arr</span>?",
    "time": 20,
    "answer": "arr.map(func)"
  },
  "answer": {
    "time": "",
    "text": ""
  }
},
{
  "question": {
    "section": "JavaScript",
    "theme": "Array",
    "text": "Функция последовательной обработки массива <span>arr</span> с сохранением промежуточного результата?",
    "time": 20,
    "answer": "arr.reduce()"
  },
  "answer": {
    "time": "",
    "text": ""
  }
},
{
  "question": {
    "section": "JavaScript",
    "theme": "Array",
    "text": "Проверка массива <span>arr</span> на соответствие всех элементов функцией <span>func</span>?",
    "time": 20,
    "answer": "arr.every(func)"
  },
  "answer": {
    "time": "",
    "text": ""
  }
},
{
  "question": {
    "section": "JavaScript",
    "theme": "Array",
    "text": "Проверка массива <span>arr</span> на соответствие любого элемента функции <span>func</span>?",
    "time": 20,
    "answer": "arr.some(func)"
  },
  "answer": {
    "time": "",
    "text": ""
  }
}]
